[
  {
    "id": "llama_2026071714",
    "source": "DeFiLlama",
    "title": "Base TVL: $4,488,149,815 🟢 +0.00% (24h)",
    "url": "https://defillama.com/chain/Base",
    "published_at": "",
    "fetched_at": "2026-07-17T14:13:38.332300+00:00",
    "used": true,
    "_sort_date": "2026-07-17T14:13:38.332300+00:00"
  },
  {
    "id": "rss_9bf20ad153ef",
    "source": "CryptoSlate",
    "title": "Bitmine nears its Ethereum buying limit – Now it needs demand to make the bet pay off",
    "url": "https://cryptoslate.com/bitmine-nears-its-ethereum-buying-limit-now-it-needs-demand-to-make-the-bet-pay-off/",
    "published_at": "Fri, 17 Jul 2026 14:45:28 +0000",
    "fetched_at": "2026-07-17T15:58:54.711266+00:00",
    "used": true,
    "_sort_date": "2026-07-17T14:45:28+00:00"
  },
  {
    "id": "llama_2026071715",
    "source": "DeFiLlama",
    "title": "Base TVL: $4,480,747,218 🟢 +0.00% (24h)",
    "url": "https://defillama.com/chain/Base",
    "published_at": "",
    "fetched_at": "2026-07-17T15:58:57.525308+00:00",
    "used": true,
    "_sort_date": "2026-07-17T15:58:57.525308+00:00"
  },
  {
    "id": "llama_2026071717",
    "source": "DeFiLlama",
    "title": "Base TVL: $4,489,986,040 🟢 +0.00% (24h)",
    "url": "https://defillama.com/chain/Base",
    "published_at": "",
    "fetched_at": "2026-07-17T17:20:18.665956+00:00",
    "used": true,
    "_sort_date": "2026-07-17T17:20:18.665956+00:00"
  },
  {
    "id": "rss_cc9cba31b136",
    "source": "Bankless",
    "title": "Ethereum Is Building Reunification Machinery",
    "url": "https://www.bankless.com/read/ethereum-is-building-reunification-machinery",
    "published_at": "Fri, 17 Jul 2026 14:35:11 -0400",
    "fetched_at": "2026-07-17T18:36:23.871551+00:00",
    "used": false,
    "_sort_date": "2026-07-17T14:35:11-04:00"
  },
  {
    "id": "llama_2026071718",
    "source": "DeFiLlama",
    "title": "Base TVL: $4,507,688,267 🟢 +0.00% (24h)",
    "url": "https://defillama.com/chain/Base",
    "published_at": "",
    "fetched_at": "2026-07-17T18:36:28.506935+00:00",
    "used": false,
    "_sort_date": "2026-07-17T18:36:28.506935+00:00"
  },
  {
    "id": "rss_579ddfa6978c",
    "source": "The Defiant",
    "title": "OKX Launches Tokenized US Stocks on Shared Order Book",
    "url": "https://thedefiant.io/converge/cefi/okx-launches-tokenized-us-stocks-on-shared-order-book",
    "published_at": "Fri, 17 Jul 2026 19:53:05 GMT",
    "fetched_at": "2026-07-17T20:11:50.633917+00:00",
    "used": true,
    "_sort_date": "2026-07-17T19:53:05+00:00"
  },
  {
    "id": "rss_e0e90516f833",
    "source": "The Defiant",
    "title": "Tokenized Stock Lending TVL Reaches $23M as DEX Volume Climbs",
    "url": "https://thedefiant.io/news/defi/tokenized-stock-lending-tvl-reaches-23m-as-dex-volume-climbs",
    "published_at": "Fri, 17 Jul 2026 19:06:48 GMT",
    "fetched_at": "2026-07-17T20:11:50.633917+00:00",
    "used": false,
    "_sort_date": "2026-07-17T19:06:48+00:00"
  },
  {
    "id": "rss_fac6d6537862",
    "source": "The Defiant",
    "title": "CASHCAT Falls 75% from Peak After Hyperliquid Perp Listing",
    "url": "https://thedefiant.io/news/tokens/cashcat-falls-75-from-peak-after-hyperliquid-perp-listing",
    "published_at": "Fri, 17 Jul 2026 18:34:57 GMT",
    "fetched_at": "2026-07-17T20:11:50.633917+00:00",
    "used": true,
    "_sort_date": "2026-07-17T18:34:57+00:00"
  },
  {
    "id": "llama_2026071720",
    "source": "DeFiLlama",
    "title": "Base TVL: $4,524,139,804 🟢 +0.00% (24h)",
    "url": "https://defillama.com/chain/Base",
    "published_at": "",
    "fetched_at": "2026-07-17T20:11:54.784346+00:00",
    "used": false,
    "_sort_date": "2026-07-17T20:11:54.784346+00:00"
  },
  {
    "id": "llama_2026071721",
    "source": "DeFiLlama",
    "title": "Base TVL: $4,531,722,575 🟢 +0.00% (24h)",
    "url": "https://defillama.com/chain/Base",
    "published_at": "",
    "fetched_at": "2026-07-17T21:24:07.365426+00:00",
    "used": false,
    "_sort_date": "2026-07-17T21:24:07.365426+00:00"
  },
  {
    "id": "llama_2026071722",
    "source": "DeFiLlama",
    "title": "Base TVL: $4,532,234,757 🟢 +0.00% (24h)",
    "url": "https://defillama.com/chain/Base",
    "published_at": "",
    "fetched_at": "2026-07-17T22:25:00.674482+00:00",
    "used": false,
    "_sort_date": "2026-07-17T22:25:00.674482+00:00"
  },
  {
    "id": "llama_2026071723",
    "source": "DeFiLlama",
    "title": "Base TVL: $4,532,209,503 🟢 +0.00% (24h)",
    "url": "https://defillama.com/chain/Base",
    "published_at": "",
    "fetched_at": "2026-07-17T23:27:45.648279+00:00",
    "used": true,
    "_sort_date": "2026-07-17T23:27:45.648279+00:00"
  },
  {
    "id": "llama_2026071801",
    "source": "DeFiLlama",
    "title": "Base TVL: $4,523,847,801 🟢 +0.00% (24h)",
    "url": "https://defillama.com/chain/Base",
    "published_at": "",
    "fetched_at": "2026-07-18T01:01:09.425026+00:00",
    "used": false,
    "_sort_date": "2026-07-18T01:01:09.425026+00:00"
  },
  {
    "id": "llama_2026071804",
    "source": "DeFiLlama",
    "title": "Base TVL: $4,527,177,465 🟢 +0.00% (24h)",
    "url": "https://defillama.com/chain/Base",
    "published_at": "",
    "fetched_at": "2026-07-18T04:29:35.006244+00:00",
    "used": true,
    "_sort_date": "2026-07-18T04:29:35.006244+00:00"
  },
  {
    "id": "rss_f901fbf6dfcf",
    "source": "Bankless",
    "title": "DeFi's Big Robinhood Chain Winners",
    "url": "https://www.bankless.com/read/defis-big-robinhood-chain-winners",
    "published_at": "Fri, 10 Jul 2026 16:13:22 -0400",
    "fetched_at": "2026-07-18T06:30:54.208124+00:00",
    "used": false
  },
  {
    "id": "llama_2026071806",
    "source": "DeFiLlama",
    "title": "Base TVL: $4,528,374,635 🟢 +0.00% (24h)",
    "url": "https://defillama.com/chain/Base",
    "published_at": "",
    "fetched_at": "2026-07-18T06:30:57.378084+00:00",
    "used": true,
    "_sort_date": "2026-07-18T06:30:57.378084+00:00"
  },
  {
    "id": "llama_2026071808",
    "source": "DeFiLlama",
    "title": "Base TVL: $4,530,483,840 🟢 +0.00% (24h)",
    "url": "https://defillama.com/chain/Base",
    "published_at": "",
    "fetched_at": "2026-07-18T08:53:53.318946+00:00",
    "used": true,
    "_sort_date": "2026-07-18T08:53:53.318946+00:00"
  },
  {
    "id": "llama_2026071810",
    "source": "DeFiLlama",
    "title": "Base TVL: $4,530,199,922 🟢 +0.00% (24h)",
    "url": "https://defillama.com/chain/Base",
    "published_at": "",
    "fetched_at": "2026-07-18T10:24:36.429359+00:00",
    "used": false,
    "_sort_date": "2026-07-18T10:24:36.429359+00:00"
  },
  {
    "id": "llama_2026071811",
    "source": "DeFiLlama",
    "title": "Base TVL: $4,528,562,182 🟢 +0.00% (24h)",
    "url": "https://defillama.com/chain/Base",
    "published_at": "",
    "fetched_at": "2026-07-18T11:31:39.888100+00:00",
    "used": false,
    "_sort_date": "2026-07-18T11:31:39.888100+00:00"
  },
  {
    "id": "llama_2026071813",
    "source": "DeFiLlama",
    "title": "Base TVL: $4,529,917,357 🟢 +0.00% (24h)",
    "url": "https://defillama.com/chain/Base",
    "published_at": "",
    "fetched_at": "2026-07-18T13:38:51.297663+00:00",
    "used": true,
    "_sort_date": "2026-07-18T13:38:51.297663+00:00"
  },
  {
    "id": "llama_2026071815",
    "source": "DeFiLlama",
    "title": "Base TVL: $4,536,030,930 🟢 +0.00% (24h)",
    "url": "https://defillama.com/chain/Base",
    "published_at": "",
    "fetched_at": "2026-07-18T15:02:39.386386+00:00",
    "used": true,
    "_sort_date": "2026-07-18T15:02:39.386386+00:00"
  },
  {
    "id": "rss_32e39275dea8",
    "source": "The Defiant",
    "title": "'Coinbase Man' Token Crashes as Armstrong Swaps His Avatar for a CryptoPunk",
    "url": "https://thedefiant.io/news/tokens/coinbase-man-token-crashes-as-armstrong-swaps-his-avatar-for-a-cryptopunk",
    "published_at": "Sat, 18 Jul 2026 15:59:24 GMT",
    "fetched_at": "2026-07-18T16:29:09.831055+00:00",
    "used": true,
    "_sort_date": "2026-07-18T15:59:24+00:00"
  },
  {
    "id": "llama_2026071816",
    "source": "DeFiLlama",
    "title": "Base TVL: $4,533,460,402 🟢 +0.00% (24h)",
    "url": "https://defillama.com/chain/Base",
    "published_at": "",
    "fetched_at": "2026-07-18T16:29:12.891796+00:00",
    "used": false,
    "_sort_date": "2026-07-18T16:29:12.891796+00:00"
  },
  {
    "id": "llama_2026071817",
    "source": "DeFiLlama",
    "title": "Base TVL: $4,538,847,500 🟢 +0.00% (24h)",
    "url": "https://defillama.com/chain/Base",
    "published_at": "",
    "fetched_at": "2026-07-18T17:36:48.675995+00:00",
    "used": false,
    "_sort_date": "2026-07-18T17:36:48.675995+00:00"
  },
  {
    "id": "llama_2026071819",
    "source": "DeFiLlama",
    "title": "Base TVL: $4,542,759,749 🟢 +0.00% (24h)",
    "url": "https://defillama.com/chain/Base",
    "published_at": "",
    "fetched_at": "2026-07-18T19:14:53.666514+00:00",
    "used": false,
    "_sort_date": "2026-07-18T19:14:53.666514+00:00"
  },
  {
    "id": "llama_2026071820",
    "source": "DeFiLlama",
    "title": "Base TVL: $4,557,636,956 🟢 +0.00% (24h)",
    "url": "https://defillama.com/chain/Base",
    "published_at": "",
    "fetched_at": "2026-07-18T20:22:39.569091+00:00",
    "used": true,
    "_sort_date": "2026-07-18T20:22:39.569091+00:00"
  },
  {
    "id": "llama_2026071821",
    "source": "DeFiLlama",
    "title": "Base TVL: $4,560,501,518 🟢 +0.00% (24h)",
    "url": "https://defillama.com/chain/Base",
    "published_at": "",
    "fetched_at": "2026-07-18T21:26:41.060577+00:00",
    "used": true,
    "_sort_date": "2026-07-18T21:26:41.060577+00:00"
  },
  {
    "id": "llama_2026071822",
    "source": "DeFiLlama",
    "title": "Base TVL: $4,561,566,224 🟢 +0.00% (24h)",
    "url": "https://defillama.com/chain/Base",
    "published_at": "",
    "fetched_at": "2026-07-18T22:26:43.671831+00:00",
    "used": false,
    "_sort_date": "2026-07-18T22:26:43.671831+00:00"
  },
  {
    "id": "llama_2026071823",
    "source": "DeFiLlama",
    "title": "Base TVL: $4,568,531,432 🟢 +0.00% (24h)",
    "url": "https://defillama.com/chain/Base",
    "published_at": "",
    "fetched_at": "2026-07-18T23:31:42.936627+00:00",
    "used": false,
    "_sort_date": "2026-07-18T23:31:42.936627+00:00"
  },
  {
    "id": "llama_2026071903",
    "source": "DeFiLlama",
    "title": "Base TVL: $4,575,153,447 🟢 +0.00% (24h)",
    "url": "https://defillama.com/chain/Base",
    "published_at": "",
    "fetched_at": "2026-07-19T03:37:15.908880+00:00",
    "used": true,
    "_sort_date": "2026-07-19T03:37:15.908880+00:00"
  },
  {
    "id": "llama_2026071906",
    "source": "DeFiLlama",
    "title": "Base TVL: $4,573,776,176 🟢 +0.00% (24h)",
    "url": "https://defillama.com/chain/Base",
    "published_at": "",
    "fetched_at": "2026-07-19T06:38:08.940113+00:00",
    "used": true,
    "_sort_date": "2026-07-19T06:38:08.940113+00:00"
  },
  {
    "id": "llama_2026071909",
    "source": "DeFiLlama",
    "title": "Base TVL: $4,577,923,277 🟢 +0.00% (24h)",
    "url": "https://defillama.com/chain/Base",
    "published_at": "",
    "fetched_at": "2026-07-19T09:09:37.062161+00:00",
    "used": true,
    "_sort_date": "2026-07-19T09:09:37.062161+00:00"
  },
  {
    "id": "rss_287140871b21",
    "source": "Cointelegraph Base",
    "title": "Moonbeam to pivot from Polkadot to Base, unveils AI agent framework",
    "url": "https://cointelegraph.com/news/moonbeam-pivots-from-polkadot-to-base-unveils-ai-agent-framework?utm_source=rss_feed&utm_medium=rss_tag_base&utm_campaign=rss_partner_inbound",
    "published_at": "Sun, 05 Jul 2026 00:50:30 +0000",
    "fetched_at": "2026-07-19T10:54:57.316539+00:00",
    "used": false
  },
  {
    "id": "llama_2026071910",
    "source": "DeFiLlama",
    "title": "Base TVL: $4,574,291,499 🟢 +0.00% (24h)",
    "url": "https://defillama.com/chain/Base",
    "published_at": "",
    "fetched_at": "2026-07-19T10:55:01.681259+00:00",
    "used": false,
    "_sort_date": "2026-07-19T10:55:01.681259+00:00"
  },
  {
    "id": "llama_2026071912",
    "source": "DeFiLlama",
    "title": "Base TVL: $4,563,627,282 🟢 +0.00% (24h)",
    "url": "https://defillama.com/chain/Base",
    "published_at": "",
    "fetched_at": "2026-07-19T12:02:44.892333+00:00",
    "used": true,
    "_sort_date": "2026-07-19T12:02:44.892333+00:00"
  },
  {
    "id": "rss_cc5d0b825c64",
    "source": "CoinDesk",
    "title": "Tether's USDT hits 2-year countdown threatening its position on U.S. crypto platforms",
    "url": "https://www.coindesk.com/news-analysis/2026/07/17/tether-s-usdt-hits-2-year-countdown-threatening-its-position-on-u-s-crypto-platforms",
    "published_at": "Sun, 19 Jul 2026 13:00:00 +0000",
    "fetched_at": "2026-07-19T14:04:45.725681+00:00",
    "used": true,
    "_sort_date": "2026-07-19T13:00:00+00:00"
  },
  {
    "id": "llama_2026071914",
    "source": "DeFiLlama",
    "title": "Base TVL: $4,563,062,980 🟢 +0.00% (24h)",
    "url": "https://defillama.com/chain/Base",
    "published_at": "",
    "fetched_at": "2026-07-19T14:04:49.559214+00:00",
    "used": false,
    "_sort_date": "2026-07-19T14:04:49.559214+00:00"
  },
  {
    "id": "llama_2026071915",
    "source": "DeFiLlama",
    "title": "Base TVL: $4,566,938,067 🟢 +0.00% (24h)",
    "url": "https://defillama.com/chain/Base",
    "published_at": "",
    "fetched_at": "2026-07-19T15:32:34.658470+00:00",
    "used": true,
    "_sort_date": "2026-07-19T15:32:34.658470+00:00"
  },
  {
    "id": "rss_93446e323342",
    "source": "CryptoSlate",
    "title": "Grayscale is setting up a quarterly cash showdown between Ethereum and Solana staking",
    "url": "https://cryptoslate.com/grayscale-is-setting-up-a-quarterly-cash-showdown-between-ethereum-and-solana-staking/",
    "published_at": "Sun, 19 Jul 2026 17:00:42 +0000",
    "fetched_at": "2026-07-19T17:07:08.783277+00:00",
    "used": true,
    "_sort_date": "2026-07-19T17:00:42+00:00"
  },
  {
    "id": "llama_2026071917",
    "source": "DeFiLlama",
    "title": "Base TVL: $4,567,067,598 🟢 +0.00% (24h)",
    "url": "https://defillama.com/chain/Base",
    "published_at": "",
    "fetched_at": "2026-07-19T17:07:11.637687+00:00",
    "used": false,
    "_sort_date": "2026-07-19T17:07:11.637687+00:00"
  },
  {
    "id": "llama_2026071918",
    "source": "DeFiLlama",
    "title": "Base TVL: $4,564,179,325 🟢 +0.00% (24h)",
    "url": "https://defillama.com/chain/Base",
    "published_at": "",
    "fetched_at": "2026-07-19T18:31:44.979054+00:00",
    "used": false,
    "_sort_date": "2026-07-19T18:31:44.979054+00:00"
  },
  {
    "id": "rss_3f4a6d72768f",
    "source": "Cointelegraph Base",
    "title": "Base says sequencer bug caused back-to-back outages",
    "url": "https://cointelegraph.com/news/base-post-mortem-reveals-sequencer-bug-behind-back-to-back-outages?utm_source=rss_feed&utm_medium=rss_tag_base&utm_campaign=rss_partner_inbound",
    "published_at": "Sun, 28 Jun 2026 05:14:05 +0000",
    "fetched_at": "2026-07-19T20:09:52.110017+00:00",
    "used": false
  },
  {
    "id": "rss_b1194184a5db",
    "source": "Cointelegraph Base",
    "title": "Coinbase's Base resumes block production after 2-hour outage",
    "url": "https://cointelegraph.com/news/coinbases-blockchain-base-back-online-after-2-hour-outage?utm_source=rss_feed&utm_medium=rss_tag_base&utm_campaign=rss_partner_inbound",
    "published_at": "Fri, 26 Jun 2026 05:10:44 +0000",
    "fetched_at": "2026-07-19T20:09:52.110017+00:00",
    "used": false
  },
  {
    "id": "rss_c3a86da63fcf",
    "source": "Cointelegraph Base",
    "title": "Travala lets AI agents book hotels with USDC on Base",
    "url": "https://cointelegraph.com/news/travala-ai-agents-book-hotels-usdc-base?utm_source=rss_feed&utm_medium=rss_tag_base&utm_campaign=rss_partner_inbound",
    "published_at": "Fri, 05 Jun 2026 19:55:27 +0000",
    "fetched_at": "2026-07-19T20:09:52.110017+00:00",
    "used": false
  },
  {
    "id": "rss_cb1f3e4f40b0",
    "source": "Cointelegraph Base",
    "title": "Agentic payment activity tops 100M transactions on Base",
    "url": "https://cointelegraph.com/news/agentic-payment-activity-surpasses-100m-transactions-on-base?utm_source=rss_feed&utm_medium=rss_tag_base&utm_campaign=rss_partner_inbound",
    "published_at": "Wed, 03 Jun 2026 16:54:33 +0000",
    "fetched_at": "2026-07-19T20:09:52.110017+00:00",
    "used": false
  },
  {
    "id": "rss_dd2b56f1e18b",
    "source": "Cointelegraph Base",
    "title": "Base launches new tool to connect crypto wallets to AI agents",
    "url": "https://cointelegraph.com/news/base-launches-mcp-ttol-to-connect-crypto-wallets-to-ai-agents?utm_source=rss_feed&utm_medium=rss_tag_base&utm_campaign=rss_partner_inbound",
    "published_at": "Wed, 27 May 2026 03:49:13 +0000",
    "fetched_at": "2026-07-19T20:09:52.110017+00:00",
    "used": false
  },
  {
    "id": "rss_d565fa6cef39",
    "source": "Cointelegraph Base",
    "title": "Syndicate Labs winds down after 5 years, citing shrinking rollup market",
    "url": "https://cointelegraph.com/news/ethereum-infrastructure-firm-syndicate-labs-closes-citing-shift-in-rollup-market?utm_source=rss_feed&utm_medium=rss_tag_base&utm_campaign=rss_partner_inbound",
    "published_at": "Thu, 21 May 2026 06:30:06 +0000",
    "fetched_at": "2026-07-19T20:09:52.110017+00:00",
    "used": false
  },
  {
    "id": "rss_e5444d8e1573",
    "source": "Cointelegraph Base",
    "title": "Circle makes USDC push into AI agent payment tools",
    "url": "https://cointelegraph.com/news/circle-unveils-agent-stack-for-ai-driven-stablecoin-transactions?utm_source=rss_feed&utm_medium=rss_tag_base&utm_campaign=rss_partner_inbound",
    "published_at": "Mon, 11 May 2026 06:00:00 +0000",
    "fetched_at": "2026-07-19T20:09:52.110017+00:00",
    "used": false
  },
  {
    "id": "rss_796a0e9ef18d",
    "source": "Cointelegraph Base",
    "title": "Coinbase and AWS launch USDC payment rails for AI agents",
    "url": "https://cointelegraph.com/news/aws-and-coinbase-launch-crypto-payment-infrastructure-for-ai-agents?utm_source=rss_feed&utm_medium=rss_tag_base&utm_campaign=rss_partner_inbound",
    "published_at": "Thu, 07 May 2026 06:00:00 +0000",
    "fetched_at": "2026-07-19T20:09:52.110017+00:00",
    "used": false
  },
  {
    "id": "rss_85a1b3339037",
    "source": "Cointelegraph Base",
    "title": "Visa adds Polygon, Base support as stablecoin settlement run rate hits $7B",
    "url": "https://cointelegraph.com/news/visa-stablecoin-settlement-polygon-base-7b-run-rate?utm_source=rss_feed&utm_medium=rss_tag_base&utm_campaign=rss_partner_inbound",
    "published_at": "Wed, 29 Apr 2026 16:21:55 +0000",
    "fetched_at": "2026-07-19T20:09:52.110017+00:00",
    "used": false
  },
  {
    "id": "rss_197ac5ad83ce",
    "source": "Cointelegraph Base",
    "title": "Base joins Ethereum, Tron, others in betting big on AI agent future",
    "url": "https://cointelegraph.com/news/base-joins-ethereum-tron-others-betting-big-ai-agent-future?utm_source=rss_feed&utm_medium=rss_tag_base&utm_campaign=rss_partner_inbound",
    "published_at": "Tue, 31 Mar 2026 14:00:00 +0000",
    "fetched_at": "2026-07-19T20:09:52.110017+00:00",
    "used": false
  },
  {
    "id": "rss_f4512c004a07",
    "source": "Cointelegraph Base",
    "title": "Dynamic adds embedded wallet infrastructure to TON for Telegram apps",
    "url": "https://cointelegraph.com/news/fireblocks-backed-dynamic-adds-embedded-wallet-infrastructure-to-ton-for-telegram-apps-embargo-tues-march-31-7am-et?utm_source=rss_feed&utm_medium=rss_tag_base&utm_campaign=rss_partner_inbound",
    "published_at": "Tue, 31 Mar 2026 12:00:00 +0000",
    "fetched_at": "2026-07-19T20:09:52.110017+00:00",
    "used": false
  },
  {
    "id": "rss_c3470a8664af",
    "source": "Cointelegraph Base",
    "title": "Mezo taps Aerodrome to support token trading on Base in Bitcoin DeFi push",
    "url": "https://cointelegraph.com/news/mezo-aerodrome-base-token-trading-bitcoin-defi?utm_source=rss_feed&utm_medium=rss_tag_base&utm_campaign=rss_partner_inbound",
    "published_at": "Thu, 26 Mar 2026 17:01:44 +0000",
    "fetched_at": "2026-07-19T20:09:52.110017+00:00",
    "used": false
  },
  {
    "id": "rss_d78072dd8b69",
    "source": "Cointelegraph Base",
    "title": "World launches AgentKit with Coinbase integration to enable human-verified AI agents",
    "url": "https://cointelegraph.com/news/world-launches-agentkit-coinbase-integration-enable-human-verified-ai-agents-embargo?utm_source=rss_feed&utm_medium=rss_tag_base&utm_campaign=rss_partner_inbound",
    "published_at": "Tue, 17 Mar 2026 15:57:47 +0000",
    "fetched_at": "2026-07-19T20:09:52.110017+00:00",
    "used": false
  },
  {
    "id": "rss_340315b7db7f",
    "source": "BlockWorks",
    "title": "ETH derivatives reset and the next retail trade",
    "url": "https://blockworks.com/news/eth-derivatives-reset",
    "published_at": "2026-01-05T15:14:17.000Z",
    "fetched_at": "2026-07-19T20:09:52.110017+00:00",
    "used": true,
    "_sort_date": "2026-07-19T20:09:52.110017+00:00"
  },
  {
    "id": "llama_2026071920",
    "source": "DeFiLlama",
    "title": "Base TVL: $4,564,376,690 🟢 +0.00% (24h)",
    "url": "https://defillama.com/chain/Base",
    "published_at": "",
    "fetched_at": "2026-07-19T20:09:54.462942+00:00",
    "used": false,
    "_sort_date": "2026-07-19T20:09:54.462942+00:00"
  },
  {
    "id": "llama_2026071921",
    "source": "DeFiLlama",
    "title": "Base TVL: $4,557,940,058 🟢 +0.00% (24h)",
    "url": "https://defillama.com/chain/Base",
    "published_at": "",
    "fetched_at": "2026-07-19T21:27:19.919598+00:00",
    "used": true,
    "_sort_date": "2026-07-19T21:27:19.919598+00:00"
  },
  {
    "id": "llama_2026071922",
    "source": "DeFiLlama",
    "title": "Base TVL: $4,558,185,637 🟢 +0.00% (24h)",
    "url": "https://defillama.com/chain/Base",
    "published_at": "",
    "fetched_at": "2026-07-19T22:28:57.906281+00:00",
    "used": false
  },
  {
    "id": "llama_2026071923",
    "source": "DeFiLlama",
    "title": "Base TVL: $4,555,252,181 🟢 +0.00% (24h)",
    "url": "https://defillama.com/chain/Base",
    "published_at": "",
    "fetched_at": "2026-07-19T23:34:02.719192+00:00",
    "used": false
  },
  {
    "id": "llama_2026072003",
    "source": "DeFiLlama",
    "title": "Base TVL: $4,573,785,845 🟢 +0.00% (24h)",
    "url": "https://defillama.com/chain/Base",
    "published_at": "",
    "fetched_at": "2026-07-20T03:51:12.827691+00:00",
    "used": true,
    "_sort_date": "2026-07-20T03:51:12.827691+00:00"
  },
  {
    "id": "llama_2026072006",
    "source": "DeFiLlama",
    "title": "Base TVL: $4,560,872,396 🟢 +0.00% (24h)",
    "url": "https://defillama.com/chain/Base",
    "published_at": "",
    "fetched_at": "2026-07-20T06:55:41.874853+00:00",
    "used": true,
    "_sort_date": "2026-07-20T06:55:41.874853+00:00"
  },
  {
    "id": "rss_74c5a2495db0",
    "source": "CryptoSlate",
    "title": "Ethereum bridge users have 24 hours to exit before chain shuts down after just 5 week warning",
    "url": "https://cryptoslate.com/ethereum-bridge-users-have-24-hours-to-exit-before-chain-shutdown-announced-just-five-weeks-ago/",
    "published_at": "Mon, 20 Jul 2026 09:44:44 +0000",
    "fetched_at": "2026-07-20T10:18:58.880207+00:00",
    "used": true,
    "_sort_date": "2026-07-20T09:44:44+00:00"
  },
  {
    "id": "llama_2026072010",
    "source": "DeFiLlama",
    "title": "Base TVL: $4,552,732,136 🟢 +0.00% (24h)",
    "url": "https://defillama.com/chain/Base",
    "published_at": "",
    "fetched_at": "2026-07-20T10:19:04.121292+00:00",
    "used": true,
    "_sort_date": "2026-07-20T10:19:04.121292+00:00"
  },
  {
    "id": "llama_2026072012",
    "source": "DeFiLlama",
    "title": "Base TVL: $4,557,087,059 🟢 +0.00% (24h)",
    "url": "https://defillama.com/chain/Base",
    "published_at": "",
    "fetched_at": "2026-07-20T12:35:05.378763+00:00",
    "used": true,
    "_sort_date": "2026-07-20T12:35:05.378763+00:00"
  },
  {
    "id": "rss_dd5706623a84",
    "source": "CoinDesk",
    "title": "Tom Lee's Bitmine slowed ether purchases as it bought back $86 million in stock",
    "url": "https://www.coindesk.com/business/2026/07/20/tom-lee-s-bitmine-slowed-ether-purchases-as-it-bought-back-usd86-million-in-stock",
    "published_at": "Mon, 20 Jul 2026 12:55:36 +0000",
    "fetched_at": "2026-07-20T15:17:11.270711+00:00",
    "used": true,
    "_sort_date": "2026-07-20T12:55:36+00:00"
  },
  {
    "id": "llama_2026072015",
    "source": "DeFiLlama",
    "title": "Base TVL: $4,551,457,055 🟢 +0.00% (24h)",
    "url": "https://defillama.com/chain/Base",
    "published_at": "",
    "fetched_at": "2026-07-20T15:17:15.388905+00:00",
    "used": true,
    "_sort_date": "2026-07-20T15:17:15.388905+00:00"
  },
  {
    "id": "rss_290e5dec73a2",
    "source": "Decrypt",
    "title": "Tom Lee's Bitmine Taps the Brakes on ETH Buys, Pivots $86M Into Stock Buyback",
    "url": "https://decrypt.co/373847/tom-lee-bitmine-taps-brakes-eth-buys-86m-stock-buyback",
    "published_at": "Mon, 20 Jul 2026 16:12:36 +0000",
    "fetched_at": "2026-07-20T17:00:38.446115+00:00",
    "used": false,
    "_sort_date": "2026-07-20T16:12:36+00:00"
  },
  {
    "id": "llama_2026072017",
    "source": "DeFiLlama",
    "title": "Base TVL: $4,572,010,907 🟢 +0.00% (24h)",
    "url": "https://defillama.com/chain/Base",
    "published_at": "",
    "fetched_at": "2026-07-20T17:00:41.849100+00:00",
    "used": false,
    "_sort_date": "2026-07-20T17:00:41.849100+00:00"
  },
  {
    "id": "rss_18e9dfd2dba6",
    "source": "The Defiant",
    "title": "Lighter Makes Stock Tokens Eligible Collateral on Robinhood Chain",
    "url": "https://thedefiant.io/news/defi/lighter-makes-stock-tokens-eligible-collateral-on-robinhood-chain",
    "published_at": "Mon, 20 Jul 2026 19:05:16 GMT",
    "fetched_at": "2026-07-20T19:14:55.848945+00:00",
    "used": true,
    "_sort_date": "2026-07-20T19:05:16+00:00"
  },
  {
    "id": "rss_570fa1870e47",
    "source": "The Defiant",
    "title": "Saylor Opposes Bitcoin's BIP-110 in 110-Point Essay",
    "url": "https://thedefiant.io/news/blockchains/saylor-opposes-bitcoin-s-bip-110-in-110-point-essay",
    "published_at": "Mon, 20 Jul 2026 18:58:13 GMT",
    "fetched_at": "2026-07-20T19:14:55.848945+00:00",
    "used": false,
    "_sort_date": "2026-07-20T18:58:13+00:00"
  },
  {
    "id": "rss_ae7b32565701",
    "source": "The Defiant",
    "title": "Hyperliquid to Open HIP-4 Prediction Markets Behind 500,000 HYPE Stake",
    "url": "https://thedefiant.io/news/defi/hyperliquid-to-open-hip-4-prediction-markets-behind-500-000-hype-stake",
    "published_at": "Mon, 20 Jul 2026 18:43:16 GMT",
    "fetched_at": "2026-07-20T19:14:55.848945+00:00",
    "used": false,
    "_sort_date": "2026-07-20T18:43:16+00:00"
  },
  {
    "id": "rss_c3b3ad2432c0",
    "source": "The Defiant",
    "title": "Allbridge Halts Core Bridge After $1.65M Flash Loan Exploit",
    "url": "https://thedefiant.io/news/hacks/allbridge-halts-core-bridge-after-1-65m-flash-loan-exploit",
    "published_at": "Mon, 20 Jul 2026 18:26:57 GMT",
    "fetched_at": "2026-07-20T19:14:55.848945+00:00",
    "used": true,
    "_sort_date": "2026-07-20T18:26:57+00:00"
  },
  {
    "id": "rss_607d9fd502bd",
    "source": "The Defiant",
    "title": "Strategy Sells $263.5M in MSTR Shares, Skips Bitcoin Again",
    "url": "https://thedefiant.io/converge/cefi/strategy-sells-263-5m-in-mstr-shares-skips-bitcoin-again",
    "published_at": "Mon, 20 Jul 2026 18:25:24 GMT",
    "fetched_at": "2026-07-20T19:14:55.848945+00:00",
    "used": false,
    "_sort_date": "2026-07-20T18:25:24+00:00"
  },
  {
    "id": "rss_ee275132b659",
    "source": "The Defiant",
    "title": "Bernstein Lifts Robinhood Target to $160 on Prediction Markets",
    "url": "https://thedefiant.io/converge/tradfi-and-fintech/bernstein-lifts-robinhood-target-to-160-on-prediction-markets",
    "published_at": "Mon, 20 Jul 2026 18:22:25 GMT",
    "fetched_at": "2026-07-20T19:14:55.848945+00:00",
    "used": false,
    "_sort_date": "2026-07-20T18:22:25+00:00"
  },
  {
    "id": "rss_c8678ce4287b",
    "source": "The Defiant",
    "title": "Bitmine Slowed ETH Buys to Smallest Weekly Pace Since June 2025",
    "url": "https://thedefiant.io/converge/tradfi-and-fintech/bitmine-slowed-eth-buys-to-smallest-weekly-pace-since-june-2025",
    "published_at": "Mon, 20 Jul 2026 18:19:02 GMT",
    "fetched_at": "2026-07-20T19:14:55.848945+00:00",
    "used": false,
    "_sort_date": "2026-07-20T18:19:02+00:00"
  },
  {
    "id": "rss_53c889499e1e",
    "source": "The Defiant",
    "title": "HYPE Spot ETFs Log First Weekly Outflow Since May",
    "url": "https://thedefiant.io/converge/markets/hype-spot-etfs-log-first-weekly-outflow-since-may",
    "published_at": "Mon, 20 Jul 2026 18:11:02 GMT",
    "fetched_at": "2026-07-20T19:14:55.848945+00:00",
    "used": false,
    "_sort_date": "2026-07-20T18:11:02+00:00"
  },
  {
    "id": "rss_aa25a3c5eb90",
    "source": "Bankless",
    "title": "Morpho Midnight and the Rate DeFi's Been Missing",
    "url": "https://www.bankless.com/read/morpho-midnight-and-the-rate-defis-been-missing",
    "published_at": "Mon, 20 Jul 2026 14:59:40 -0400",
    "fetched_at": "2026-07-20T19:14:55.848945+00:00",
    "used": false,
    "_sort_date": "2026-07-20T14:59:40-04:00"
  },
  {
    "id": "llama_2026072019",
    "source": "DeFiLlama",
    "title": "Base TVL: $4,614,916,376 🟢 +0.00% (24h)",
    "url": "https://defillama.com/chain/Base",
    "published_at": "",
    "fetched_at": "2026-07-20T19:14:59.613889+00:00",
    "used": false,
    "_sort_date": "2026-07-20T19:14:59.613889+00:00"
  },
  {
    "id": "rss_c4ed29038a4b",
    "source": "The Defiant",
    "title": "Consensys Halted MetaMask Releases Over North Korea-Linked Contractor",
    "url": "https://thedefiant.io/news/security/consensys-halted-metamask-releases-over-north-korea-linked-contractor",
    "published_at": "Mon, 20 Jul 2026 19:18:03 GMT",
    "fetched_at": "2026-07-20T20:49:55.969242+00:00",
    "used": true,
    "_sort_date": "2026-07-20T19:18:03+00:00"
  },
  {
    "id": "llama_2026072020",
    "source": "DeFiLlama",
    "title": "Base TVL: $4,606,218,713 🟢 +0.00% (24h)",
    "url": "https://defillama.com/chain/Base",
    "published_at": "",
    "fetched_at": "2026-07-20T20:49:59.607541+00:00",
    "used": false,
    "_sort_date": "2026-07-20T20:49:59.607541+00:00"
  },
  {
    "id": "rss_a766a72dcf62",
    "source": "The Defiant",
    "title": "Armstrong Says His X Posts and Avatars Are Not Token Endorsements",
    "url": "https://thedefiant.io/news/people/armstrong-says-his-x-posts-and-avatars-are-not-token-endorsements",
    "published_at": "Mon, 20 Jul 2026 22:07:26 GMT",
    "fetched_at": "2026-07-20T22:07:24.830112+00:00",
    "used": false
  },
  {
    "id": "rss_f62f6b075404",
    "source": "The Defiant",
    "title": "BitMine Adds $73 Million in ETH, Pushing Holdings to 4.8% of Supply",
    "url": "https://thedefiant.io/news/tradfi-and-fintech/bitmine-adds-73-million-in-eth-pushing-holdings-to-4-8-of-supply",
    "published_at": "Mon, 20 Jul 2026 22:07:26 GMT",
    "fetched_at": "2026-07-20T22:07:24.830112+00:00",
    "used": false
  },
  {
    "id": "llama_2026072022",
    "source": "DeFiLlama",
    "title": "Base TVL: $4,607,886,469 🟢 +0.00% (24h)",
    "url": "https://defillama.com/chain/Base",
    "published_at": "",
    "fetched_at": "2026-07-20T22:07:27.355796+00:00",
    "used": false
  },
  {
    "id": "llama_2026072023",
    "source": "DeFiLlama",
    "title": "Base TVL: $4,610,622,142 🟢 +0.00% (24h)",
    "url": "https://defillama.com/chain/Base",
    "published_at": "",
    "fetched_at": "2026-07-20T23:33:24.279077+00:00",
    "used": true,
    "_sort_date": "2026-07-20T23:33:24.279077+00:00"
  },
  {
    "id": "llama_2026072103",
    "source": "DeFiLlama",
    "title": "Base TVL: $4,620,806,390 🟢 +0.00% (24h)",
    "url": "https://defillama.com/chain/Base",
    "published_at": "",
    "fetched_at": "2026-07-21T03:31:03.262669+00:00",
    "used": false,
    "_sort_date": "2026-07-21T03:31:03.262669+00:00"
  },
  {
    "id": "llama_2026072106",
    "source": "DeFiLlama",
    "title": "Base TVL: $4,626,285,336 🟢 +0.00% (24h)",
    "url": "https://defillama.com/chain/Base",
    "published_at": "",
    "fetched_at": "2026-07-21T06:36:10.574646+00:00",
    "used": false,
    "_sort_date": "2026-07-21T06:36:10.574646+00:00"
  },
  {
    "id": "rss_18d775190419",
    "source": "Cointelegraph Base",
    "title": "Base’s 1:1-backed tokenized equities launch ‘imminent,’ Pollak says",
    "url": "https://cointelegraph.com/news/bases-tokenized-equities-imminent-pollak?utm_source=rss_feed&utm_medium=rss_tag_base&utm_campaign=rss_partner_inbound",
    "published_at": "Tue, 21 Jul 2026 07:06:12 +0000",
    "fetched_at": "2026-07-21T09:32:14.969419+00:00",
    "used": true,
    "_sort_date": "2026-07-21T07:06:12+00:00"
  },
  {
    "id": "llama_2026072109",
    "source": "DeFiLlama",
    "title": "Base TVL: $4,661,788,654 🟢 +0.00% (24h)",
    "url": "https://defillama.com/chain/Base",
    "published_at": "",
    "fetched_at": "2026-07-21T09:32:18.276196+00:00",
    "used": true,
    "_sort_date": "2026-07-21T09:32:18.276196+00:00"
  },
  {
    "id": "rss_40c5af511b55",
    "source": "CoinDesk",
    "title": "Bitcoin rally has broad-based support as institutions, whales, options traders pile in",
    "url": "https://www.coindesk.com/daybook-us/2026/07/21/bitcoin-rally-has-broad-based-support-as-institutions-whales-options-traders-pile-in",
    "published_at": "Tue, 21 Jul 2026 11:37:22 +0000",
    "fetched_at": "2026-07-21T11:52:28.544006+00:00",
    "used": false,
    "_sort_date": "2026-07-21T11:37:22+00:00"
  },
  {
    "id": "rss_9adbb8b0455a",
    "source": "CoinDesk",
    "title": "Clarity odds jump to 43% on Polymarket after unverified reports Trump agreed to ethics deal",
    "url": "https://www.coindesk.com/markets/2026/07/21/clarity-act-odds-jump-11-points-on-polymarket-after-reports-trump-agreed-to-ethics-deal",
    "published_at": "Tue, 21 Jul 2026 11:19:18 +0000",
    "fetched_at": "2026-07-21T11:52:28.544006+00:00",
    "used": false,
    "_sort_date": "2026-07-21T11:19:18+00:00"
  },
  {
    "id": "llama_2026072111",
    "source": "DeFiLlama",
    "title": "Base TVL: $4,670,343,316 🟢 +0.00% (24h)",
    "url": "https://defillama.com/chain/Base",
    "published_at": "",
    "fetched_at": "2026-07-21T11:52:31.473991+00:00",
    "used": false,
    "_sort_date": "2026-07-21T11:52:31.473991+00:00"
  },
  {
    "id": "rss_7ea39b4659c7",
    "source": "CoinDesk",
    "title": "Jack Mallers steps down as XXI Capital CEO as Tether's plans to merge three bitcoin firms falls",
    "url": "https://www.coindesk.com/business/2026/07/21/jack-mallers-steps-down-as-xxi-capital-ceo-as-tether-s-plans-to-merge-three-bitcoin-firms-falls",
    "published_at": "Tue, 21 Jul 2026 12:42:29 +0000",
    "fetched_at": "2026-07-21T14:10:52.982607+00:00",
    "used": false,
    "_sort_date": "2026-07-21T12:42:29+00:00"
  },
  {
    "id": "rss_665ad930eba0",
    "source": "The Defiant",
    "title": "Grayscale Files S-1 for Spot Worldcoin ETF",
    "url": "https://thedefiant.io/converge/tradfi-and-fintech/grayscale-files-s-1-for-spot-worldcoin-etf",
    "published_at": "Tue, 21 Jul 2026 13:55:00 GMT",
    "fetched_at": "2026-07-21T14:10:52.982607+00:00",
    "used": true,
    "_sort_date": "2026-07-21T13:55:00+00:00"
  },
  {
    "id": "llama_2026072114",
    "source": "DeFiLlama",
    "title": "Base TVL: $4,657,669,034 🟢 +0.00% (24h)",
    "url": "https://defillama.com/chain/Base",
    "published_at": "",
    "fetched_at": "2026-07-21T14:10:55.509794+00:00",
    "used": false,
    "_sort_date": "2026-07-21T14:10:55.509794+00:00"
  },
  {
    "id": "rss_7dec21351e01",
    "source": "The Defiant",
    "title": "Morpho Launches Fixed-Rate Lending Protocol Midnight on Base",
    "url": "https://thedefiant.io/news/defi/morpho-launches-fixed-rate-lending-protocol-midnight-on-base",
    "published_at": "Tue, 21 Jul 2026 15:47:12 GMT",
    "fetched_at": "2026-07-21T16:04:19.336978+00:00",
    "used": true,
    "_sort_date": "2026-07-21T15:47:12+00:00"
  },
  {
    "id": "rss_2d5d164dc3b8",
    "source": "The Defiant",
    "title": "Jack Mallers Steps Down as CEO of Twenty One Capital",
    "url": "https://thedefiant.io/news/people/jack-mallers-steps-down-as-ceo-of-twenty-one-capital",
    "published_at": "Tue, 21 Jul 2026 15:35:19 GMT",
    "fetched_at": "2026-07-21T16:04:19.336978+00:00",
    "used": false,
    "_sort_date": "2026-07-21T15:35:19+00:00"
  },
  {
    "id": "rss_cbeae27737eb",
    "source": "The Defiant",
    "title": "Aztec Launches Alpha V5 on Mainnet With Faster Private Proving",
    "url": "https://thedefiant.io/news/blockchains/aztec-launches-alpha-v5-on-mainnet-with-faster-private-proving",
    "published_at": "Tue, 21 Jul 2026 14:16:39 GMT",
    "fetched_at": "2026-07-21T16:04:19.336978+00:00",
    "used": false,
    "_sort_date": "2026-07-21T14:16:39+00:00"
  },
  {
    "id": "rss_01c8af02e98c",
    "source": "CryptoSlate",
    "title": "BitMine is now $484 million away from completing its 5% Ethereum target",
    "url": "https://cryptoslate.com/bitmine-is-now-484-million-away-from-completing-its-5-ethereum-target/",
    "published_at": "Tue, 21 Jul 2026 15:30:35 +0000",
    "fetched_at": "2026-07-21T16:04:19.336978+00:00",
    "used": true,
    "_sort_date": "2026-07-21T15:30:35+00:00"
  },
  {
    "id": "llama_2026072116",
    "source": "DeFiLlama",
    "title": "Base TVL: $4,682,767,797 🟢 +0.00% (24h)",
    "url": "https://defillama.com/chain/Base",
    "published_at": "",
    "fetched_at": "2026-07-21T16:04:22.653103+00:00",
    "used": false,
    "_sort_date": "2026-07-21T16:04:22.653103+00:00"
  },
  {
    "id": "rss_ebc636629674",
    "source": "The Defiant",
    "title": "Durov Says Telegram Will Ship Native Gram Wallet to a Billion Users",
    "url": "https://thedefiant.io/news/blockchains/durov-says-telegram-will-ship-native-gram-wallet-to-a-billion-users",
    "published_at": "Tue, 21 Jul 2026 16:55:18 GMT",
    "fetched_at": "2026-07-21T17:54:36.894081+00:00",
    "used": false,
    "_sort_date": "2026-07-21T16:55:18+00:00"
  },
  {
    "id": "rss_742c42e91389",
    "source": "The Defiant",
    "title": "Ondo Enables Tokenized Stock Collateral on OndoPerps",
    "url": "https://thedefiant.io/converge/defi/ondo-enables-tokenized-stock-collateral-on-ondoperps",
    "published_at": "Tue, 21 Jul 2026 16:30:52 GMT",
    "fetched_at": "2026-07-21T17:54:36.894081+00:00",
    "used": false,
    "_sort_date": "2026-07-21T16:30:52+00:00"
  },
  {
    "id": "rss_91757923542d",
    "source": "The Defiant",
    "title": "Pump.fun Adds 'BOOST' Liquidity Mode for Every New Coin",
    "url": "https://thedefiant.io/news/defi/pump-fun-adds-boost-liquidity-mode-for-every-new-coin",
    "published_at": "Tue, 21 Jul 2026 16:04:38 GMT",
    "fetched_at": "2026-07-21T17:54:36.894081+00:00",
    "used": false,
    "_sort_date": "2026-07-21T16:04:38+00:00"
  },
  {
    "id": "rss_31a4e77b75c8",
    "source": "CryptoSlate",
    "title": "Trump backs crypto ethics limits, putting CLARITY Act decision in Democrats’ hands",
    "url": "https://cryptoslate.com/trump-backs-crypto-ethics-limits-putting-clarity-act-decision-in-democrats-hands/",
    "published_at": "Tue, 21 Jul 2026 17:30:50 +0000",
    "fetched_at": "2026-07-21T17:54:36.894081+00:00",
    "used": false,
    "_sort_date": "2026-07-21T17:30:50+00:00"
  },
  {
    "id": "rss_647053a66874",
    "source": "Decrypt",
    "title": "Jack Mallers Quits Twenty One Capital as Tether's Bitcoin Merger Collapses",
    "url": "https://decrypt.co/373940/jack-mallers-quits-twenty-one-capital-as-tethers-bitcoin-merger-collapses",
    "published_at": "Tue, 21 Jul 2026 16:06:20 +0000",
    "fetched_at": "2026-07-21T17:54:36.894081+00:00",
    "used": false,
    "_sort_date": "2026-07-21T16:06:20+00:00"
  },
  {
    "id": "llama_2026072117",
    "source": "DeFiLlama",
    "title": "Base TVL: $4,688,927,082 🟢 +0.00% (24h)",
    "url": "https://defillama.com/chain/Base",
    "published_at": "",
    "fetched_at": "2026-07-21T17:54:40.355832+00:00",
    "used": false,
    "_sort_date": "2026-07-21T17:54:40.355832+00:00"
  },
  {
    "id": "rss_b9fad81acbde",
    "source": "CoinDesk",
    "title": "White House pushes Senate Democrats to take 'historic' crypto Clarity Act ethics deal",
    "url": "https://www.coindesk.com/policy/2026/07/21/white-house-pushes-senate-democrats-to-take-historic-crypto-clarity-act-ethics-deal",
    "published_at": "Tue, 21 Jul 2026 18:14:39 +0000",
    "fetched_at": "2026-07-21T19:43:12.001589+00:00",
    "used": false,
    "_sort_date": "2026-07-21T18:14:39+00:00"
  },
  {
    "id": "rss_320433978fde",
    "source": "The Defiant",
    "title": "NEAR Governance Votes to Scrap Developer Gas Rebate",
    "url": "https://thedefiant.io/news/blockchains/near-governance-votes-to-scrap-developer-gas-rebate",
    "published_at": "Tue, 21 Jul 2026 19:43:13 GMT",
    "fetched_at": "2026-07-21T19:43:12.001589+00:00",
    "used": true,
    "_sort_date": "2026-07-21T19:43:13+00:00"
  },
  {
    "id": "rss_88bc616eacb4",
    "source": "The Defiant",
    "title": "Tether's Former CIO Heathcote Plans to Sell Equity Stake",
    "url": "https://thedefiant.io/converge/cefi/tether-s-former-cio-heathcote-plans-to-sell-equity-stake",
    "published_at": "Tue, 21 Jul 2026 19:43:13 GMT",
    "fetched_at": "2026-07-21T19:43:12.001589+00:00",
    "used": false,
    "_sort_date": "2026-07-21T19:43:13+00:00"
  },
  {
    "id": "rss_0bce9827f60d",
    "source": "The Defiant",
    "title": "Crypto's Quiet Revolution: How Stablecoins Deliver Aid Where Banks Can't",
    "url": "https://thedefiant.io/podcasts-and-videos/videos/crypto-s-quiet-revolution-how-stablecoins-deliver-aid-where-banks-can-t",
    "published_at": "Tue, 21 Jul 2026 18:45:22 GMT",
    "fetched_at": "2026-07-21T19:43:12.001589+00:00",
    "used": false,
    "_sort_date": "2026-07-21T18:45:22+00:00"
  },
  {
    "id": "llama_2026072119",
    "source": "DeFiLlama",
    "title": "Base TVL: $4,677,774,460 🟢 +0.00% (24h)",
    "url": "https://defillama.com/chain/Base",
    "published_at": "",
    "fetched_at": "2026-07-21T19:43:15.246930+00:00",
    "used": false,
    "_sort_date": "2026-07-21T19:43:15.246930+00:00"
  },
  {
    "id": "rss_8cf45f3e45d8",
    "source": "CoinDesk",
    "title": "Crypto Clarity Act still at mercy of ethics section as Democrats balk at Trump deal",
    "url": "https://www.coindesk.com/policy/2026/07/21/crypto-clarity-act-still-at-mercy-of-ethics-section-as-democrats-balk-at-trump-deal",
    "published_at": "Tue, 21 Jul 2026 21:14:03 +0000",
    "fetched_at": "2026-07-21T21:19:24.749768+00:00",
    "used": false,
    "_sort_date": "2026-07-21T21:14:03+00:00"
  },
  {
    "id": "rss_6be86e66b27f",
    "source": "The Defiant",
    "title": "S&P and Pantera Launch Revenue-Screened Digital Asset Index",
    "url": "https://thedefiant.io/converge/tradfi-and-fintech/s-p-and-pantera-launch-revenue-screened-digital-asset-index",
    "published_at": "Tue, 21 Jul 2026 20:53:27 GMT",
    "fetched_at": "2026-07-21T21:19:24.749768+00:00",
    "used": false,
    "_sort_date": "2026-07-21T20:53:27+00:00"
  },
  {
    "id": "rss_4837333c220f",
    "source": "The Defiant",
    "title": "Movement Labs Files for Chapter 11 Bankruptcy",
    "url": "https://thedefiant.io/news/blockchains/movement-labs-files-for-chapter-11-bankruptcy",
    "published_at": "Tue, 21 Jul 2026 20:51:46 GMT",
    "fetched_at": "2026-07-21T21:19:24.749768+00:00",
    "used": true,
    "_sort_date": "2026-07-21T20:51:46+00:00"
  },
  {
    "id": "rss_cd070cb81389",
    "source": "Bankless",
    "title": "The Buy ETH, Sell Gold Trade?",
    "url": "https://www.bankless.com/read/the-buy-eth-sell-gold-trade",
    "published_at": "Tue, 21 Jul 2026 16:09:32 -0400",
    "fetched_at": "2026-07-21T21:19:24.749768+00:00",
    "used": false,
    "_sort_date": "2026-07-21T16:09:32-04:00"
  },
  {
    "id": "rss_3cb512204bfc",
    "source": "Bankless",
    "title": "Galaxy Debuts GOFR to Pipe Institutions Into DeFi Credit",
    "url": "https://www.bankless.com/read/news/galaxy-debuts-gofr-to-pipe-institutions-into-defi-credit",
    "published_at": "Tue, 14 Jul 2026 13:26:16 -0400",
    "fetched_at": "2026-07-21T21:19:24.749768+00:00",
    "used": false
  },
  {
    "id": "rss_ebc655ba7422",
    "source": "Bankless",
    "title": "Ethereum Foundation Privacy Team Spins Out as EthSystems",
    "url": "https://www.bankless.com/read/news/ethereum-foundation-privacy-team-spins-out-as-ethsystems",
    "published_at": "Tue, 14 Jul 2026 12:59:48 -0400",
    "fetched_at": "2026-07-21T21:19:24.749768+00:00",
    "used": false
  },
  {
    "id": "llama_2026072121",
    "source": "DeFiLlama",
    "title": "Base TVL: $4,670,001,642 🟢 +0.00% (24h)",
    "url": "https://defillama.com/chain/Base",
    "published_at": "",
    "fetched_at": "2026-07-21T21:19:27.769938+00:00",
    "used": true,
    "_sort_date": "2026-07-21T21:19:27.769938+00:00"
  },
  {
    "id": "rss_ca2ad0ed4b6e",
    "source": "The Defiant",
    "title": "Crypto Rallies as Reported Ethics Deal Revives Odds of CLARITY Act Senate Vote",
    "url": "https://thedefiant.io/converge/regulation/crypto-rallies-as-reported-ethics-deal-revives-odds-of-clarity-act-senate-vote",
    "published_at": "Tue, 21 Jul 2026 21:10:57 GMT",
    "fetched_at": "2026-07-21T22:28:56.770207+00:00",
    "used": false
  },
  {
    "id": "llama_2026072122",
    "source": "DeFiLlama",
    "title": "Base TVL: $4,678,405,282 🟢 +0.00% (24h)",
    "url": "https://defillama.com/chain/Base",
    "published_at": "",
    "fetched_at": "2026-07-21T22:29:00.035220+00:00",
    "used": false
  },
  {
    "id": "llama_2026072123",
    "source": "DeFiLlama",
    "title": "Base TVL: $4,675,533,409 🟢 +0.00% (24h)",
    "url": "https://defillama.com/chain/Base",
    "published_at": "",
    "fetched_at": "2026-07-21T23:35:00.878312+00:00",
    "used": false,
    "_sort_date": "2026-07-21T23:35:00.878312+00:00"
  },
  {
    "id": "llama_2026072203",
    "source": "DeFiLlama",
    "title": "Base TVL: $4,692,489,209 🟢 +0.00% (24h)",
    "url": "https://defillama.com/chain/Base",
    "published_at": "",
    "fetched_at": "2026-07-22T03:29:52.008556+00:00",
    "used": true,
    "_sort_date": "2026-07-22T03:29:52.008556+00:00"
  },
  {
    "id": "llama_2026072206",
    "source": "DeFiLlama",
    "title": "Base TVL: $4,678,329,511 🟢 +0.00% (24h)",
    "url": "https://defillama.com/chain/Base",
    "published_at": "",
    "fetched_at": "2026-07-22T06:12:44.679979+00:00",
    "used": true,
    "_sort_date": "2026-07-22T06:12:44.679979+00:00"
  },
  {
    "id": "llama_2026072209",
    "source": "DeFiLlama",
    "title": "Base TVL: $4,651,774,096 🟢 +0.00% (24h)",
    "url": "https://defillama.com/chain/Base",
    "published_at": "",
    "fetched_at": "2026-07-22T09:11:36.625500+00:00",
    "used": true,
    "_sort_date": "2026-07-22T09:11:36.625500+00:00"
  },
  {
    "id": "rss_a202dcb3e4a7",
    "source": "Decrypt",
    "title": "Jack Dorsey's Block Launches Buzz, a Nostr-Based Slack and GitHub Rival for AI Agents",
    "url": "https://decrypt.co/374026/jack-dorseys-block-launches-buzz-a-nostr-based-slack-and-github-rival-for-ai-agents",
    "published_at": "Wed, 22 Jul 2026 11:03:43 +0000",
    "fetched_at": "2026-07-22T11:26:24.051835+00:00",
    "used": true,
    "_sort_date": "2026-07-22T11:03:43+00:00"
  },
  {
    "id": "llama_2026072211",
    "source": "DeFiLlama",
    "title": "Base TVL: $4,652,275,811 🟢 +0.00% (24h)",
    "url": "https://defillama.com/chain/Base",
    "published_at": "",
    "fetched_at": "2026-07-22T11:26:30.293574+00:00",
    "used": false,
    "_sort_date": "2026-07-22T11:26:30.293574+00:00"
  },
  {
    "id": "llama_2026072213",
    "source": "DeFiLlama",
    "title": "Base TVL: $4,659,419,673 🟢 +0.00% (24h)",
    "url": "https://defillama.com/chain/Base",
    "published_at": "",
    "fetched_at": "2026-07-22T13:05:04.914262+00:00",
    "used": false,
    "_sort_date": "2026-07-22T13:05:04.914262+00:00"
  },
  {
    "id": "rss_2a117730c167",
    "source": "Decrypt",
    "title": "Centralized Elements 'Frequently Persist' in DeFi and Should Be Regulated: FATF",
    "url": "https://decrypt.co/374041/centralized-elements-frequently-persist-in-defi-and-should-be-regulated-fatf",
    "published_at": "Wed, 22 Jul 2026 14:41:56 +0000",
    "fetched_at": "2026-07-22T15:21:02.356310+00:00",
    "used": true,
    "_sort_date": "2026-07-22T14:41:56+00:00"
  },
  {
    "id": "llama_2026072215",
    "source": "DeFiLlama",
    "title": "Base TVL: $4,639,935,693 🟢 +0.00% (24h)",
    "url": "https://defillama.com/chain/Base",
    "published_at": "",
    "fetched_at": "2026-07-22T15:21:06.209965+00:00",
    "used": true,
    "_sort_date": "2026-07-22T15:21:06.209965+00:00"
  },
  {
    "id": "rss_6d029e63bdb4",
    "source": "CoinDesk",
    "title": "New Clarity Act emerges that's a start on the final draft, makes ethics rule temporary",
    "url": "https://www.coindesk.com/policy/2026/07/22/new-clarity-act-emerges-that-s-a-start-on-the-final-draft-makes-ethics-rule-temporary",
    "published_at": "Wed, 22 Jul 2026 16:15:55 +0000",
    "fetched_at": "2026-07-22T16:57:36.591776+00:00",
    "used": false,
    "_sort_date": "2026-07-22T16:15:55+00:00"
  },
  {
    "id": "rss_6db6ec211e98",
    "source": "CoinDesk",
    "title": "SEC's Peirce warns some DeFi vaults, onchain lending may fall under securities laws",
    "url": "https://www.coindesk.com/policy/2026/07/22/sec-s-peirce-warns-some-defi-vaults-onchain-lending-may-fall-under-securities-laws",
    "published_at": "Wed, 22 Jul 2026 15:37:36 +0000",
    "fetched_at": "2026-07-22T16:57:36.591776+00:00",
    "used": false,
    "_sort_date": "2026-07-22T15:37:36+00:00"
  },
  {
    "id": "rss_0371f395e3cb",
    "source": "CoinDesk",
    "title": "UK digital bond plans hinge on one missing piece: onchain cash",
    "url": "https://www.coindesk.com/business/2026/07/22/uk-digital-bond-plans-hinge-on-one-missing-piece-onchain-cash",
    "published_at": "Wed, 22 Jul 2026 15:36:49 +0000",
    "fetched_at": "2026-07-22T16:57:36.591776+00:00",
    "used": false,
    "_sort_date": "2026-07-22T15:36:49+00:00"
  },
  {
    "id": "llama_2026072216",
    "source": "DeFiLlama",
    "title": "Base TVL: $4,652,338,296 🟢 +0.00% (24h)",
    "url": "https://defillama.com/chain/Base",
    "published_at": "",
    "fetched_at": "2026-07-22T16:57:40.616638+00:00",
    "used": false,
    "_sort_date": "2026-07-22T16:57:40.616638+00:00"
  },
  {
    "id": "rss_55d8e3eebc5e",
    "source": "The Defiant",
    "title": "Franklin Templeton Says Altcoins Are Key to the Agentic AI Trade",
    "url": "https://thedefiant.io/converge/tradfi-and-fintech/franklin-templeton-says-altcoins-are-key-to-the-agentic-ai-trade",
    "published_at": "Wed, 22 Jul 2026 17:48:54 GMT",
    "fetched_at": "2026-07-22T18:17:09.824761+00:00",
    "used": true,
    "_sort_date": "2026-07-22T17:48:54+00:00"
  },
  {
    "id": "rss_4a14beef082b",
    "source": "The Defiant",
    "title": "Ramp Adds Stablecoin Accounts and Bill Pay on Stripe Stack",
    "url": "https://thedefiant.io/converge/tradfi-and-fintech/ramp-adds-stablecoin-accounts-and-bill-pay-on-stripe-stack",
    "published_at": "Wed, 22 Jul 2026 17:44:07 GMT",
    "fetched_at": "2026-07-22T18:17:09.824761+00:00",
    "used": false,
    "_sort_date": "2026-07-22T17:44:07+00:00"
  },
  {
    "id": "llama_2026072218",
    "source": "DeFiLlama",
    "title": "Base TVL: $4,674,406,407 🟢 +0.00% (24h)",
    "url": "https://defillama.com/chain/Base",
    "published_at": "",
    "fetched_at": "2026-07-22T18:17:13.752136+00:00",
    "used": false,
    "_sort_date": "2026-07-22T18:17:13.752136+00:00"
  },
  {
    "id": "rss_14e3026da474",
    "source": "The Defiant",
    "title": "EDX Markets Closes $76M Series C Led by SBI Holdings",
    "url": "https://thedefiant.io/converge/tradfi-and-fintech/edx-markets-closes-76m-series-c-led-by-sbi-holdings",
    "published_at": "Wed, 22 Jul 2026 19:53:41 GMT",
    "fetched_at": "2026-07-22T19:53:39.092551+00:00",
    "used": false,
    "_sort_date": "2026-07-22T19:53:41+00:00"
  },
  {
    "id": "rss_1c831db54374",
    "source": "The Defiant",
    "title": "Tokenized Stocks Hit Records Across Every Major Venue as Sector Reaches $2.3B",
    "url": "https://thedefiant.io/converge/tradfi-and-fintech/tokenized-stocks-hit-records-across-every-major-venue-as-sector-reaches-usd2-3b",
    "published_at": "Wed, 22 Jul 2026 19:24:35 GMT",
    "fetched_at": "2026-07-22T19:53:39.092551+00:00",
    "used": false,
    "_sort_date": "2026-07-22T19:24:35+00:00"
  },
  {
    "id": "rss_fcd5075bb199",
    "source": "The Defiant",
    "title": "Robinhood Chain Overtakes Base on Daily Active Users Three Weeks After Launch",
    "url": "https://thedefiant.io/news/defi/robinhood-chain-overtakes-base-on-daily-active-users-three-weeks-after-launch",
    "published_at": "Wed, 22 Jul 2026 19:07:23 GMT",
    "fetched_at": "2026-07-22T19:53:39.092551+00:00",
    "used": true,
    "_sort_date": "2026-07-22T19:07:23+00:00"
  },
  {
    "id": "rss_293166a6b44c",
    "source": "The Defiant",
    "title": "Ostium to Reopen Trading July 23 After $23.8M Vault Exploit",
    "url": "https://thedefiant.io/news/defi/ostium-to-reopen-trading-july-23-after-23-8m-vault-exploit",
    "published_at": "Wed, 22 Jul 2026 18:43:10 GMT",
    "fetched_at": "2026-07-22T19:53:39.092551+00:00",
    "used": false,
    "_sort_date": "2026-07-22T18:43:10+00:00"
  },
  {
    "id": "rss_ea5e63361d25",
    "source": "Bankless",
    "title": "DeFi's Due Diligence Super Tool",
    "url": "https://www.bankless.com/read/herd-defis-due-diligence-super-tool",
    "published_at": "Wed, 22 Jul 2026 15:46:29 -0400",
    "fetched_at": "2026-07-22T19:53:39.092551+00:00",
    "used": false,
    "_sort_date": "2026-07-22T15:46:29-04:00"
  },
  {
    "id": "llama_2026072219",
    "source": "DeFiLlama",
    "title": "Base TVL: $4,679,877,355 🟢 +0.00% (24h)",
    "url": "https://defillama.com/chain/Base",
    "published_at": "",
    "fetched_at": "2026-07-22T19:53:42.434718+00:00",
    "used": false,
    "_sort_date": "2026-07-22T19:53:42.434718+00:00"
  },
  {
    "id": "rss_e05c815b0859",
    "source": "The Defiant",
    "title": "SummerFi to Wind Down After Seven Years, Citing Exploit",
    "url": "https://thedefiant.io/news/defi/summerfi-to-wind-down-after-seven-years-citing-exploit",
    "published_at": "Wed, 22 Jul 2026 21:21:45 GMT",
    "fetched_at": "2026-07-22T21:21:42.408594+00:00",
    "used": true,
    "_sort_date": "2026-07-22T21:21:45+00:00"
  },
  {
    "id": "rss_598e41b281ec",
    "source": "Decrypt",
    "title": "Coinbase Wants to Be Canada's One-Stop Shop for Stocks, Crypto and Prediction Markets",
    "url": "https://decrypt.co/374110/coinbase-canada-stocks-crypto-prediction-markets",
    "published_at": "Wed, 22 Jul 2026 21:13:04 +0000",
    "fetched_at": "2026-07-22T21:21:42.408594+00:00",
    "used": false,
    "_sort_date": "2026-07-22T21:13:04+00:00"
  },
  {
    "id": "llama_2026072221",
    "source": "DeFiLlama",
    "title": "Base TVL: $4,659,311,425 🟢 +0.00% (24h)",
    "url": "https://defillama.com/chain/Base",
    "published_at": "",
    "fetched_at": "2026-07-22T21:21:46.996666+00:00",
    "used": false,
    "_sort_date": "2026-07-22T21:21:46.996666+00:00"
  },
  {
    "id": "rss_dc3c18dcaed0",
    "source": "CoinDesk",
    "title": "Key Democratic lawmakers say crypto Clarity Act 'falls short' on ethics, other issues",
    "url": "https://www.coindesk.com/policy/2026/07/22/key-democratic-lawmakers-say-crypto-clarity-act-falls-short-on-ethics-other-issues",
    "published_at": "Wed, 22 Jul 2026 22:22:25 +0000",
    "fetched_at": "2026-07-22T22:35:59.245372+00:00",
    "used": false
  },
  {
    "id": "rss_6a75079cdd8b",
    "source": "The Defiant",
    "title": "Crypto Industry Pushes for Senate Vote on New CLARITY Act Text as Democrats Blast Ethics Plan",
    "url": "https://thedefiant.io/converge/regulation/crypto-industry-pushes-for-senate-vote-on-new-clarity-act-text-as-democrats-blast-ethics-plan",
    "published_at": "Wed, 22 Jul 2026 21:21:28 GMT",
    "fetched_at": "2026-07-22T22:35:59.245372+00:00",
    "used": false
  },
  {
    "id": "llama_2026072222",
    "source": "DeFiLlama",
    "title": "Base TVL: $4,666,528,971 🟢 +0.00% (24h)",
    "url": "https://defillama.com/chain/Base",
    "published_at": "",
    "fetched_at": "2026-07-22T22:36:01.900365+00:00",
    "used": false
  },
  {
    "id": "rss_21d2364d8b26",
    "source": "CoinDesk",
    "title": "Senator Lummis: Ethics, other provisions in crypto Clarity Act to be further discussed",
    "url": "https://www.coindesk.com/policy/2026/07/22/senator-lummis-ethics-other-provisions-in-crypto-clarity-act-to-be-further-discussed",
    "published_at": "Wed, 22 Jul 2026 23:19:41 +0000",
    "fetched_at": "2026-07-23T00:08:19.751090+00:00",
    "used": false,
    "_sort_date": "2026-07-22T23:19:41+00:00"
  },
  {
    "id": "llama_2026072300",
    "source": "DeFiLlama",
    "title": "Base TVL: $4,656,925,989 🟢 +0.00% (24h)",
    "url": "https://defillama.com/chain/Base",
    "published_at": "",
    "fetched_at": "2026-07-23T00:08:23.528368+00:00",
    "used": false,
    "_sort_date": "2026-07-23T00:08:23.528368+00:00"
  },
  {
    "id": "rss_4a6869ec1d39",
    "source": "The Defiant",
    "title": "Attacker Drains $24M in USDC From AFX Bridge on Arbitrum",
    "url": "https://thedefiant.io/news/hacks/attacker-drains-usd24m-in-usdc-from-afx-bridge-on-arbitrum",
    "published_at": "Thu, 23 Jul 2026 01:35:03 GMT",
    "fetched_at": "2026-07-23T03:56:20.568491+00:00",
    "used": false,
    "_sort_date": "2026-07-23T01:35:03+00:00"
  },
  {
    "id": "llama_2026072303",
    "source": "DeFiLlama",
    "title": "Base TVL: $4,644,446,667 🟢 +0.00% (24h)",
    "url": "https://defillama.com/chain/Base",
    "published_at": "",
    "fetched_at": "2026-07-23T03:56:23.580525+00:00",
    "used": false,
    "_sort_date": "2026-07-23T03:56:23.580525+00:00"
  },
  {
    "id": "rss_3cbb9fdb2d7f",
    "source": "Cointelegraph Base",
    "title": "Base’s social bet left it trailing in prediction markets and perps: Pollak",
    "url": "https://cointelegraph.com/news/bases-social-bet-left-it-trailing-in-prediction-markets-and-perps-pollak?utm_source=rss_feed&utm_medium=rss_tag_base&utm_campaign=rss_partner_inbound",
    "published_at": "Thu, 16 Jul 2026 01:14:58 +0000",
    "fetched_at": "2026-07-23T06:36:59.938106+00:00",
    "used": false
  },
  {
    "id": "rss_ab3a02f48e67",
    "source": "CoinDesk",
    "title": "Arbitrum-based AFX Trade drained of $24 million after bridge keys compromised",
    "url": "https://www.coindesk.com/tech/2026/07/23/arbitrum-based-afx-trade-drained-of-usd24-million-after-bridge-keys-compromised",
    "published_at": "Thu, 23 Jul 2026 05:01:06 +0000",
    "fetched_at": "2026-07-23T06:36:59.938106+00:00",
    "used": true,
    "_sort_date": "2026-07-23T05:01:06+00:00"
  },
  {
    "id": "llama_2026072306",
    "source": "DeFiLlama",
    "title": "Base TVL: $4,629,893,556 🟢 +0.00% (24h)",
    "url": "https://defillama.com/chain/Base",
    "published_at": "",
    "fetched_at": "2026-07-23T06:37:03.170745+00:00",
    "used": false,
    "_sort_date": "2026-07-23T06:37:03.170745+00:00"
  },
  {
    "id": "rss_9335ad855f79",
    "source": "CoinDesk",
    "title": "Bitcoin, Ethereum-linked protocols lose $35 million in multiple attacks hours apart",
    "url": "https://www.coindesk.com/tech/2026/07/23/bitcoin-ethereum-linked-protocols-lose-usd35-million-in-multiple-attacks-hours-apart",
    "published_at": "Thu, 23 Jul 2026 06:38:18 +0000",
    "fetched_at": "2026-07-23T09:29:33.998569+00:00",
    "used": true,
    "_sort_date": "2026-07-23T06:38:18+00:00"
  },
  {
    "id": "llama_2026072309",
    "source": "DeFiLlama",
    "title": "Base TVL: $4,621,369,277 🟢 +0.00% (24h)",
    "url": "https://defillama.com/chain/Base",
    "published_at": "",
    "fetched_at": "2026-07-23T09:29:38.131032+00:00",
    "used": true,
    "_sort_date": "2026-07-23T09:29:38.131032+00:00"
  },
  {
    "id": "rss_683d8c2b2394",
    "source": "CryptoSlate",
    "title": "Bitcoin rose 2% on CLARITY progress while Coinbase, Circle jumped over 8% – but why?",
    "url": "https://cryptoslate.com/bitcoin-rose-2-on-clarity-progress-while-coinbase-circle-jumped-over-8-but-why/",
    "published_at": "Thu, 23 Jul 2026 11:10:19 +0000",
    "fetched_at": "2026-07-23T11:28:09.117530+00:00",
    "used": false,
    "_sort_date": "2026-07-23T11:10:19+00:00"
  },
  {
    "id": "llama_2026072311",
    "source": "DeFiLlama",
    "title": "Base TVL: $4,626,937,414 🟢 +0.00% (24h)",
    "url": "https://defillama.com/chain/Base",
    "published_at": "",
    "fetched_at": "2026-07-23T11:28:16.600392+00:00",
    "used": false,
    "_sort_date": "2026-07-23T11:28:16.600392+00:00"
  },
  {
    "id": "rss_94f0fd4bdf4d",
    "source": "CoinDesk",
    "title": "BlackRock, Coinbase, Strategy in group pledging $15 million to prepare Bitcoin for quantum threats",
    "url": "https://www.coindesk.com/business/2026/07/23/blackrock-coinbase-strategy-in-group-pledging-usd15-million-to-prepare-bitcoin-for-quantum-threats",
    "published_at": "Thu, 23 Jul 2026 12:54:27 +0000",
    "fetched_at": "2026-07-23T13:08:17.790197+00:00",
    "used": false,
    "_sort_date": "2026-07-23T12:54:27+00:00"
  },
  {
    "id": "rss_7c5b73a77b42",
    "source": "CoinDesk",
    "title": "Abu Dhabi's Mubadala Capital joins tokenization push as Coinbase takes stake in onchain fund",
    "url": "https://www.coindesk.com/business/2026/07/23/abu-dhabi-s-mubadala-capital-joins-tokenization-push-as-coinbase-takes-stake-in-onchain-fund",
    "published_at": "Thu, 23 Jul 2026 12:00:00 +0000",
    "fetched_at": "2026-07-23T13:08:17.790197+00:00",
    "used": false,
    "_sort_date": "2026-07-23T12:00:00+00:00"
  },
  {
    "id": "rss_f0c3388bb02c",
    "source": "Decrypt",
    "title": "Morning Minute: Wall Street Moving Onchain Will Drive the Next Bull Market",
    "url": "https://decrypt.co/374139/morning-minute-wall-street-moving-onchain-will-drive-the-next-bull-market",
    "published_at": "Thu, 23 Jul 2026 12:02:52 +0000",
    "fetched_at": "2026-07-23T13:08:17.790197+00:00",
    "used": true,
    "_sort_date": "2026-07-23T12:02:52+00:00"
  },
  {
    "id": "llama_2026072313",
    "source": "DeFiLlama",
    "title": "Base TVL: $4,621,622,698 🟢 +0.00% (24h)",
    "url": "https://defillama.com/chain/Base",
    "published_at": "",
    "fetched_at": "2026-07-23T13:08:21.653291+00:00",
    "used": false,
    "_sort_date": "2026-07-23T13:08:21.653291+00:00"
  },
  {
    "id": "rss_358c4fd6015b",
    "source": "CoinDesk",
    "title": "Uniswap pushes deeper into tokenized assets with permissioned trading pools",
    "url": "https://www.coindesk.com/business/2026/07/22/uniswap-pushes-deeper-into-tokenized-assets-with-permissioned-trading-pools",
    "published_at": "Thu, 23 Jul 2026 14:00:00 +0000",
    "fetched_at": "2026-07-23T15:33:45.055522+00:00",
    "used": false,
    "_sort_date": "2026-07-23T14:00:00+00:00"
  },
  {
    "id": "rss_2e473dc068dd",
    "source": "CryptoSlate",
    "title": "White House pushes back as key Democrats rejects CLARITY Act’s crypto ethics",
    "url": "https://cryptoslate.com/white-house-pushes-back-as-key-democrats-rejects-clarity-acts-crypto-ethics/",
    "published_at": "Thu, 23 Jul 2026 14:05:28 +0000",
    "fetched_at": "2026-07-23T15:33:45.055522+00:00",
    "used": false,
    "_sort_date": "2026-07-23T14:05:28+00:00"
  },
  {
    "id": "rss_cb21a198fc8d",
    "source": "CryptoSlate",
    "title": "Latest $3.8 billion RWA recovery shows how quickly DeFi absorbed the KelpDAO shock",
    "url": "https://cryptoslate.com/a-3-8-billion-rwa-recovery-shows-how-quickly-defi-absorbed-the-kelpdao-shock/",
    "published_at": "Thu, 23 Jul 2026 13:10:17 +0000",
    "fetched_at": "2026-07-23T15:33:45.055522+00:00",
    "used": false,
    "_sort_date": "2026-07-23T13:10:17+00:00"
  },
  {
    "id": "rss_c98d0b9ec6ad",
    "source": "Decrypt",
    "title": "BlackRock, Coinbase and Strategy Pledge $15M to Quantum-Proof Bitcoin",
    "url": "https://decrypt.co/374145/blackrock-coinbase-strategy-15m-quantum-proof-bitcoin",
    "published_at": "Thu, 23 Jul 2026 15:17:38 +0000",
    "fetched_at": "2026-07-23T15:33:45.055522+00:00",
    "used": true,
    "_sort_date": "2026-07-23T15:17:38+00:00"
  },
  {
    "id": "llama_2026072315",
    "source": "DeFiLlama",
    "title": "Base TVL: $4,589,040,676 🟢 +0.00% (24h)",
    "url": "https://defillama.com/chain/Base",
    "published_at": "",
    "fetched_at": "2026-07-23T15:33:48.440932+00:00",
    "used": true,
    "_sort_date": "2026-07-23T15:33:48.440932+00:00"
  },
  {
    "id": "rss_60eb7ba1822b",
    "source": "CoinDesk",
    "title": "Coinbase's corporate customers can now accept payments from AI agents",
    "url": "https://www.coindesk.com/business/2026/07/23/coinbase-closes-the-gaps-in-ai-agent-economy-for-businesses-users-and-developers",
    "published_at": "Thu, 23 Jul 2026 16:54:12 +0000",
    "fetched_at": "2026-07-23T17:39:33.217431+00:00",
    "used": true,
    "_sort_date": "2026-07-23T16:54:12+00:00"
  },
  {
    "id": "rss_3bfe4064ae89",
    "source": "CoinDesk",
    "title": "The SEC settles with Coinbase over its missing Gary Gensler texts",
    "url": "https://www.coindesk.com/policy/2026/07/23/sec-agrees-to-end-lawsuit-over-missing-ethereum-records-will-pay-usd150-000-in-fees",
    "published_at": "Thu, 23 Jul 2026 15:36:39 +0000",
    "fetched_at": "2026-07-23T17:39:33.217431+00:00",
    "used": false,
    "_sort_date": "2026-07-23T15:36:39+00:00"
  },
  {
    "id": "rss_3d68db85dfe7",
    "source": "The Defiant",
    "title": "Ondo's Oasis Pro Markets Cleared to Offer Tokenized Stocks in US",
    "url": "https://thedefiant.io/converge/tradfi-and-fintech/ondo-s-oasis-pro-markets-cleared-to-offer-tokenized-stocks-in-us",
    "published_at": "Thu, 23 Jul 2026 17:17:09 GMT",
    "fetched_at": "2026-07-23T17:39:33.217431+00:00",
    "used": false,
    "_sort_date": "2026-07-23T17:17:09+00:00"
  },
  {
    "id": "rss_8a14ff8ad227",
    "source": "The Defiant",
    "title": "Uniswap Adds Permissioned Pools to Bring Regulated Assets to v4",
    "url": "https://thedefiant.io/news/defi/uniswap-adds-permissioned-pools-to-bring-regulated-assets-to-v4",
    "published_at": "Thu, 23 Jul 2026 16:56:43 GMT",
    "fetched_at": "2026-07-23T17:39:33.217431+00:00",
    "used": false,
    "_sort_date": "2026-07-23T16:56:43+00:00"
  },
  {
    "id": "rss_d33b291a54e6",
    "source": "The Defiant",
    "title": "KAIO Tokenizes Mubadala Capital Fund Across Base, Solana and Sui",
    "url": "https://thedefiant.io/converge/tradfi-and-fintech/kaio-tokenizes-mubadala-capital-fund-across-base-solana-and-sui",
    "published_at": "Thu, 23 Jul 2026 16:41:02 GMT",
    "fetched_at": "2026-07-23T17:39:33.217431+00:00",
    "used": false,
    "_sort_date": "2026-07-23T16:41:02+00:00"
  },
  {
    "id": "rss_2859e47c25f8",
    "source": "The Defiant",
    "title": "SEC's Peirce Says Onchain Vaults, Lending Can Trigger Securities Laws",
    "url": "https://thedefiant.io/news/regulation/sec-s-peirce-says-onchain-vaults-lending-can-trigger-securities-laws",
    "published_at": "Thu, 23 Jul 2026 16:13:49 GMT",
    "fetched_at": "2026-07-23T17:39:33.217431+00:00",
    "used": false,
    "_sort_date": "2026-07-23T16:13:49+00:00"
  },
  {
    "id": "rss_a459440daf55",
    "source": "The Defiant",
    "title": "BitMEX to Shut Down Exchange on Sept. 23, Urges Withdrawals",
    "url": "https://thedefiant.io/converge/cefi/bitmex-to-shut-down-exchange-on-sept-23-urges-withdrawals",
    "published_at": "Thu, 23 Jul 2026 15:58:36 GMT",
    "fetched_at": "2026-07-23T17:39:33.217431+00:00",
    "used": false,
    "_sort_date": "2026-07-23T15:58:36+00:00"
  },
  {
    "id": "rss_127e5ddac42f",
    "source": "CryptoSlate",
    "title": "$460 billion Bitcoin risk draws BlackRock, Coinbase and Strategy into $15M quantum defense mission",
    "url": "https://cryptoslate.com/460-billion-bitcoin-risk-draws-blackrock-coinbase-and-strategy-into-15m-quantum-computing-defense-push/",
    "published_at": "Thu, 23 Jul 2026 16:05:22 +0000",
    "fetched_at": "2026-07-23T17:39:33.217431+00:00",
    "used": false,
    "_sort_date": "2026-07-23T16:05:22+00:00"
  },
  {
    "id": "llama_2026072317",
    "source": "DeFiLlama",
    "title": "Base TVL: $4,587,875,907 🟢 +0.00% (24h)",
    "url": "https://defillama.com/chain/Base",
    "published_at": "",
    "fetched_at": "2026-07-23T17:39:43.710969+00:00",
    "used": false,
    "_sort_date": "2026-07-23T17:39:43.710969+00:00"
  },
  {
    "id": "rss_9c2b18ab89c0",
    "source": "CryptoSlate",
    "title": "SEC pays $150,000 as Coinbase-backed Freedom Of Information Act settlement releases two withheld documents",
    "url": "https://cryptoslate.com/sec-pays-150000-as-coinbase-backed-freedom-of-information-act-settlement-releases-two-withheld-documents/",
    "published_at": "Thu, 23 Jul 2026 19:05:38 +0000",
    "fetched_at": "2026-07-23T19:37:27.966910+00:00",
    "used": true,
    "_sort_date": "2026-07-23T19:05:38+00:00"
  },
  {
    "id": "rss_9a3845e79a80",
    "source": "Bankless",
    "title": "The SEC Puts DeFi Vaults on Notice",
    "url": "https://www.bankless.com/read/the-sec-puts-defi-vaults-on-notice",
    "published_at": "Thu, 23 Jul 2026 13:58:04 -0400",
    "fetched_at": "2026-07-23T19:37:27.966910+00:00",
    "used": false,
    "_sort_date": "2026-07-23T13:58:04-04:00"
  },
  {
    "id": "llama_2026072319",
    "source": "DeFiLlama",
    "title": "Base TVL: $4,592,213,633 🟢 +0.00% (24h)",
    "url": "https://defillama.com/chain/Base",
    "published_at": "",
    "fetched_at": "2026-07-23T19:37:30.479432+00:00",
    "used": false,
    "_sort_date": "2026-07-23T19:37:30.479432+00:00"
  },
  {
    "id": "rss_1593f6d708a4",
    "source": "The Defiant",
    "title": "Hacker Behind Fake 'Vladhood' Token Still Collecting Fees After Robinhood CEO's X Account Hack",
    "url": "https://thedefiant.io/news/defi/hacker-behind-fake-vladhood-token-still-collecting-fees-after-robinhood-ceo-s-x-account-hack",
    "published_at": "Thu, 23 Jul 2026 20:25:12 GMT",
    "fetched_at": "2026-07-23T21:14:16.281210+00:00",
    "used": true,
    "_sort_date": "2026-07-23T20:25:12+00:00"
  },
  {
    "id": "llama_2026072321",
    "source": "DeFiLlama",
    "title": "Base TVL: $4,588,201,470 🟢 +0.00% (24h)",
    "url": "https://defillama.com/chain/Base",
    "published_at": "",
    "fetched_at": "2026-07-23T21:14:21.906987+00:00",
    "used": false,
    "_sort_date": "2026-07-23T21:14:21.906987+00:00"
  },
  {
    "id": "llama_2026072322",
    "source": "DeFiLlama",
    "title": "Base TVL: $4,599,124,998 🟢 +0.00% (24h)",
    "url": "https://defillama.com/chain/Base",
    "published_at": "",
    "fetched_at": "2026-07-23T22:32:34.672171+00:00",
    "used": false
  },
  {
    "id": "llama_2026072400",
    "source": "DeFiLlama",
    "title": "Base TVL: $4,597,261,709 🟢 +0.00% (24h)",
    "url": "https://defillama.com/chain/Base",
    "published_at": "",
    "fetched_at": "2026-07-24T00:06:21.620992+00:00",
    "used": false,
    "_sort_date": "2026-07-24T00:06:21.620992+00:00"
  },
  {
    "id": "rss_c930ff31d118",
    "source": "Bankless",
    "title": "Ethereum Researcher Francesco D'Amato Departs EF for Ethlabs",
    "url": "https://www.bankless.com/read/news/ethereum-researcher-francesco-damato-departs-ef-for-ethlabs",
    "published_at": "Thu, 16 Jul 2026 14:50:51 -0400",
    "fetched_at": "2026-07-24T03:55:28.426780+00:00",
    "used": false
  },
  {
    "id": "llama_2026072403",
    "source": "DeFiLlama",
    "title": "Base TVL: $4,597,105,840 🟢 +0.00% (24h)",
    "url": "https://defillama.com/chain/Base",
    "published_at": "",
    "fetched_at": "2026-07-24T03:55:31.663111+00:00",
    "used": false,
    "_sort_date": "2026-07-24T03:55:31.663111+00:00"
  },
  {
    "id": "rss_fcc111fc916e",
    "source": "CoinDesk",
    "title": "Mirae plans to turn crypto exchange Korbit into something Korea hasn't seen before",
    "url": "https://www.coindesk.com/markets/2026/07/24/mirae-asset-has-a-name-for-what-it-s-building-with-korbit-an-intelligent-platform",
    "published_at": "Fri, 24 Jul 2026 06:10:49 +0000",
    "fetched_at": "2026-07-24T06:34:43.443097+00:00",
    "used": true,
    "_sort_date": "2026-07-24T06:10:49+00:00"
  },
  {
    "id": "rss_f6c703321b45",
    "source": "The Defiant",
    "title": "eToro Takes Strategic Stake in Onchain Derivatives Exchange Extended, Plans Zengo Tie-Up",
    "url": "https://thedefiant.io/news/cefi/etoro-strategic-stake-onchain-derivatives-extended-zengo",
    "published_at": "Fri, 24 Jul 2026 06:34:45 GMT",
    "fetched_at": "2026-07-24T06:34:43.443097+00:00",
    "used": true,
    "_sort_date": "2026-07-24T06:34:45+00:00"
  },
  {
    "id": "llama_2026072406",
    "source": "DeFiLlama",
    "title": "Base TVL: $4,614,157,676 🟢 +0.00% (24h)",
    "url": "https://defillama.com/chain/Base",
    "published_at": "",
    "fetched_at": "2026-07-24T06:34:47.573213+00:00",
    "used": false,
    "_sort_date": "2026-07-24T06:34:47.573213+00:00"
  },
  {
    "id": "rss_78126e065469",
    "source": "CoinDesk",
    "title": "Live updates: Dogecoin and ether lead pullback as investors digest tech earnings",
    "url": "https://www.coindesk.com/tech/2026/07/24/live-updates-dogecoin-and-ether-lead-pullback-as-investors-digest-tech-earnings",
    "published_at": "Fri, 24 Jul 2026 07:22:26 +0000",
    "fetched_at": "2026-07-24T09:26:54.266895+00:00",
    "used": true,
    "_sort_date": "2026-07-24T07:22:26+00:00"
  },
  {
    "id": "llama_2026072409",
    "source": "DeFiLlama",
    "title": "Base TVL: $4,630,169,865 🟢 +0.00% (24h)",
    "url": "https://defillama.com/chain/Base",
    "published_at": "",
    "fetched_at": "2026-07-24T09:26:59.394931+00:00",
    "used": false,
    "_sort_date": "2026-07-24T09:26:59.394931+00:00"
  },
  {
    "id": "llama_2026072411",
    "source": "DeFiLlama",
    "title": "Base TVL: $4,615,122,014 🟢 +0.00% (24h)",
    "url": "https://defillama.com/chain/Base",
    "published_at": "",
    "fetched_at": "2026-07-24T11:19:38.019677+00:00",
    "used": false
  },
  {
    "id": "rss_e5b72f6da9e5",
    "source": "CryptoSlate",
    "title": "DeFi’s next institutional hurdle is deciding who can be trusted to price real-world assets",
    "url": "https://cryptoslate.com/defis-next-institutional-hurdle-is-deciding-who-can-be-trusted-to-price-the-collateral/",
    "published_at": "Fri, 24 Jul 2026 11:30:49 +0000",
    "fetched_at": "2026-07-24T13:03:30.131100+00:00",
    "used": false
  },
  {
    "id": "llama_2026072413",
    "source": "DeFiLlama",
    "title": "Base TVL: $4,600,250,659 🟢 +0.00% (24h)",
    "url": "https://defillama.com/chain/Base",
    "published_at": "",
    "fetched_at": "2026-07-24T13:03:34.796630+00:00",
    "used": false
  }
]